clkUnit/clkUnit.vhd
library IEEE;
use IEEE.std_logic_1164.all;

entity clkUnit is
  
 port (
   clk, reset : in  std_logic;
   enableTX   : out std_logic;
   enableRX   : out std_logic);
    
end clkUnit;

architecture behavorial of clkUnit is

begin
	enableRX <= clk when (reset ='1') else '0' ;

  div : process (clk, reset)
    variable cpt : integer range 0 to 15 := 0;
  begin
  
	if (reset ='0') then 
		enableTX <= '0';
      cpt := 0;
			
   elsif rising_edge(clk) then
	   if(cpt = 15) then
        cpt := 0;
      else
        cpt := cpt + 1;
      end if;
		
      if cpt = 0 then
        enableTX <= '1';
      else
        enableTX <= '0';
      end if;

	end if;
  end process;

end behavorial;

TxUnit/TxUnit.vhd
library IEEE;
use IEEE.std_logic_1164.all;

entity TxUnit is
  port (
    clk, reset : in std_logic;
    enable : in std_logic;
    ld : in std_logic;
    txd : out std_logic;
    regE : out std_logic;
    bufE : out std_logic; --'0' = occupe
    data : in std_logic_vector(7 downto 0));
end TxUnit;

architecture behavorial of TxUnit is
type t_etats is(premier, deuxieme, troisieme, quatrieme, cinquieme, sixieme);
signal etat : t_etats;
signal registreT : std_logic_vector(7 downto 0);--registre de data
signal bufferT : std_logic_vector(7 downto 0);--registre de data
signal parite : std_logic;--bit de parité
signal bufEbis : std_logic;--signal interne permet l'utilisation du buffer dans fonction conditionnelle

--signaux si besoin
begin
process (clk,reset)
--variables si besoin
variable cpt : natural;

begin
	if (reset ='0') then 
		txd <='1';
		regE<='1';
		bufE<='1';
		bufEbis <='1';
		registreT<= (others => '0');
		cpt := 7;
		parite <= '0';
		etat <= premier;
	
	--Si le buffer est vide et qu'on veut load une data à l'étape 3, 4, 5 ou 6 alors on remplit le buffer 
	elsif (rising_edge(clk)) then 
		if ((etat = troisieme or etat =quatrieme or etat =cinquieme or etat =sixieme) and bufEbis ='1' and ld='1') then 
			bufferT <= data;
			bufE <='0';
			bufEbis<='0';
		end if;
		
		case etat is

			--état de repos si ld='0' quand ld='1' on met la data dans le buffer
			when premier => 
				if (ld='1') then 
					bufferT<=data;
					bufEbis<='0';
					bufE <= '0';
					etat <= deuxieme;
				end if;

			--on fait passer la data du buffer au registre et on vide le buffer.
			when deuxieme =>
				registreT<=bufferT;
				regE<='0';
				bufEbis<= '1';
				bufE <= '1';
				etat <= troisieme;

			--on envoie le bit de start et on initialise le compteur à 7
			when troisieme =>
				if (enable ='1') then 
					txd <='0';
					parite <= '0'; --réinitialisation du bit de parite
					cpt := 7;
					etat <= quatrieme;
				end if;

			--On envoie les données au travers de TxD
			when quatrieme =>
				if (enable ='1') then
					--Une fois que toute les données sont envoyées, on vide le registre
					if (cpt=0) then
					    txd<=registreT(cpt);
						parite<= parite xor registreT(cpt);
						regE<='1';
						etat <= cinquieme;
					--On envoie sur TxD bit par bit et on met à jours le bit de parité
					else
						txd<=registreT(cpt);
						parite<= parite xor registreT(cpt);
						cpt:=cpt-1;
					end if;
				end if;

			--Envoie du bit de parite
			when cinquieme =>
				if (enable ='1') then 
					txd <=parite;
					etat <= sixieme;
				end if;
			
			--Envoie du bit de stop et on passe à l'étape 2 si buffer non vide ou étape 1 sinon
			when sixieme =>
				if (enable = '1') then 
					txd <= '1';
					if (bufEbis ='0') then 
						etat <= deuxieme;
					else 
						etat <= premier;
					end if;
				end if;

			end case;
		end if;
	end process;
end behavorial;

TxUnit/testTxUnit.vhd
--------------------------------------------------------------------------------
-- Company: 
-- Engineer:
--
-- Create Date:   12:09:49 10/31/2018
-- Design Name:   
-- Module Name:   testTxUnit.vhd
-- Project Name:  uart
-- Target Device:  
-- Tool versions:  
-- Description:   
-- 
-- VHDL Test Bench Created by ISE for module: TxUnit
-- 
-- Dependencies:
-- 
-- Revision:
-- Revision 0.01 - File Created
-- Additional Comments:
--
-- Notes: 
-- This testbench has been automatically generated using types std_logic and
-- std_logic_vector for the ports of the unit under test.  Xilinx recommends
-- that these types always be used for the top-level I/O of a design in order
-- to guarantee that the testbench will bind correctly to the post-implementation 
-- simulation model.
--------------------------------------------------------------------------------
LIBRARY ieee;
USE ieee.std_logic_1164.ALL;
 
-- Uncomment the following library declaration if using
-- arithmetic functions with Signed or Unsigned values
--USE ieee.numeric_std.ALL;
 
ENTITY testTxUnit IS
END testTxUnit;
 
ARCHITECTURE behavior OF testTxUnit IS 
 
    -- Component Declaration for the Unit Under Test (UUT)
 
    COMPONENT TxUnit
    PORT(
         clk : IN  std_logic;
         reset : IN  std_logic;
         enable : IN  std_logic;
         ld : IN  std_logic;
         txd : OUT  std_logic;
         regE : OUT  std_logic;
         bufE : OUT  std_logic;
         data : IN  std_logic_vector(7 downto 0)
        );
    END COMPONENT;
   
    COMPONENT clkUnit
    PORT(
         clk : IN  std_logic;
         reset : IN  std_logic;
         enableTX : OUT  std_logic;
         enableRX : OUT  std_logic
        );
    END COMPONENT;	

   signal clk : std_logic := '0';
   signal reset : std_logic := '0';
   signal enableTx : std_logic := '0';
   signal enableRx : std_logic := '0';
   signal ld : std_logic := '0';
   signal data : std_logic_vector(7 downto 0) := (others => '0');

   signal txd : std_logic;
   signal regE : std_logic;
   signal bufE : std_logic;
	
   -- Clock period definitions
   constant clk_period : time := 10 ns;
 
BEGIN
 
	-- Instantiate the Unit Under Test
   uut0: TxUnit PORT MAP (
          clk => clk,
          reset => reset,
          enable => enableTX,
          ld => ld,
          txd => txd,
          regE => regE,
          bufE => bufE,
          data => data
        );

   -- Instantiate the clkUnit
   clkUnit1: clkUnit PORT MAP (
          clk => clk,
          reset => reset,
          enableTX => enableTX,
          enableRX => enableRX
        );
		  
   -- Clock process definitions
   clk_process :process
   begin
     clk <= '0';
     wait for clk_period/2;
     clk <= '1';
     wait for clk_period/2;
   end process;
 
 
   -- Stimulus process
   stim_proc: process
   begin		
     -- maintien du reset durant 100 ns.
     wait for 100 ns;	
     reset <= '1';

     wait for 200 ns;


     -- si oui, on charge la donnée
     wait for clk_period;
     -- émission du caractère 0x55
     data <= "01010101";
     ld <= '1';

     -- on attend de voir que l'ordre d'émission
     -- a été bien pris en compte avant de rabaisser
     -- le signal ld
     if not (regE='1' and bufE='0') then
       wait until regE='1' and bufE='0';
     end if;
     wait for clk_period;
     ld <= '0';
		
	  wait for clk_period*50;
     
	data <= "11110101";
     ld <= '1';

     -- on attend de voir que l'ordre d'émission
     -- a été bien pris en compte avant de rabaisser
     -- le signal ld
     if not (regE='1' and bufE='0') then
       wait until regE='1' and bufE='0';
     end if;
     wait for clk_period;
     ld <= '0';
	  
	  wait for clk_period*200;
  
	data <= "01010001";
     ld <= '1';

     -- on attend de voir que l'ordre d'émission
     -- a été bien pris en compte avant de rabaisser
     -- le signal ld
     if not (regE='1' and bufE='0') then
       wait until regE='1' and bufE='0';
     end if;
     wait for clk_period;
     ld <= '0';
    
     wait for clk_period*200;

  data <= "00001111";
     ld <= '1';

     -- on attend de voir que l'ordre d'émission
     -- a été bien pris en compte avant de rabaisser
     -- le signal ld
     if not (regE='1' and bufE='0') then
       wait until regE='1' and bufE='0';
     end if;
     wait for clk_period;
     ld <= '0';
	  
	  wait for clk_period*220;
  
  data <= "11110000";
    ld <= '1';

    -- on attend de voir que l'ordre d'émission
    -- a été bien pris en compte avant de rabaisser
    -- le signal ld
    if not (regE='1' and bufE='0') then
      wait until regE='1' and bufE='0';
    end if;
    wait for clk_period;
    ld <= '0';
   
   wait;
  
   end process;

END;

TxUnit/output.vcd
$date
   Tue Jan 18 18:31:59 2022
$end
$version
  P.20131013
$end
$timescale
  1ps
$end
$scope module testtxunit $end
$var wire 1 S clk $end
$var wire 1 T reset $end
$var wire 1 U enabletx $end
$var wire 1 V enablerx $end
$var wire 1 4 ld $end
$var wire 1 ? data [7] $end
$var wire 1 > data [6] $end
$var wire 1 = data [5] $end
$var wire 1 < data [4] $end
$var wire 1 ; data [3] $end
$var wire 1 : data [2] $end
$var wire 1 9 data [1] $end
$var wire 1 8 data [0] $end
$var wire 1 5 txd $end
$var wire 1 6 rege $end
$var wire 1 7 bufe $end
$scope module uut0 $end
$var wire 1 S clk $end
$var wire 1 T reset $end
$var wire 1 U enable $end
$var wire 1 4 ld $end
$var wire 1 5 txd $end
$var wire 1 6 rege $end
$var wire 1 7 bufe $end
$var wire 1 ? data [7] $end
$var wire 1 > data [6] $end
$var wire 1 = data [5] $end
$var wire 1 < data [4] $end
$var wire 1 ; data [3] $end
$var wire 1 : data [2] $end
$var wire 1 9 data [1] $end
$var wire 1 8 data [0] $end
$var wire 1 H registret [7] $end
$var wire 1 G registret [6] $end
$var wire 1 F registret [5] $end
$var wire 1 E registret [4] $end
$var wire 1 D registret [3] $end
$var wire 1 C registret [2] $end
$var wire 1 B registret [1] $end
$var wire 1 A registret [0] $end
$var wire 1 P buffert [7] $end
$var wire 1 O buffert [6] $end
$var wire 1 N buffert [5] $end
$var wire 1 M buffert [4] $end
$var wire 1 L buffert [3] $end
$var wire 1 K buffert [2] $end
$var wire 1 J buffert [1] $end
$var wire 1 I buffert [0] $end
$var wire 1 Q parite $end
$var wire 1 R bufebis $end
$upscope $end
$scope module clkUnit1 $end
$var wire 1 S clk $end
$var wire 1 T reset $end
$var wire 1 U enabletx $end
$var wire 1 V enablerx $end
$upscope $end
$upscope $end
$enddefinitions $end
#0
$dumpvars
0T
0U
0V
04
0?
0>
0=
0<
0;
0:
09
08
15
16
17
0H
0G
0F
0E
0D
0C
0B
0A
xP
xO
xN
xM
xL
xK
xJ
xI
0Q
1R
0S
$end
#5000
1S
#10000
0S
#15000
1S
#20000
0S
#25000
1S
#30000
0S
#35000
1S
#40000
0S
#45000
1S
#50000
0S
#55000
1S
#60000
0S
#65000
1S
#70000
0S
#75000
1S
#80000
0S
#85000
1S
#90000
0S
#95000
1S
#100000
1T
0S
#105000
1V
1S
#110000
0V
0S
#115000
1V
1S
#120000
0V
0S
#125000
1V
1S
#130000
0V
0S
#135000
1V
1S
#140000
0V
0S
#145000
1V
1S
#150000
0V
0S
#155000
1V
1S
#160000
0V
0S
#165000
1V
1S
#170000
0V
0S
#175000
1V
1S
#180000
0V
0S
#185000
1V
1S
#190000
0V
0S
#195000
1V
1S
#200000
0V
0S
#205000
1V
1S
#210000
0V
0S
#215000
1V
1S
#220000
0V
0S
#225000
1V
1S
#230000
0V
0S
#235000
1V
1S
#240000
0V
0S
#245000
1V
1S
#250000
0V
0S
#255000
1U
1V
1S
#260000
0V
0S
#265000
0U
1V
1S
#270000
0V
0S
#275000
1V
1S
#280000
0V
0S
#285000
1V
1S
#290000
0V
0S
#295000
1V
1S
#300000
0V
0S
#305000
1V
1S
#310000
0V
14
1>
1<
1:
18
0S
#315000
1V
07
0P
1O
0N
1M
0L
1K
0J
1I
0R
1S
#320000
0V
0S
#325000
1V
04
06
17
1G
1E
1C
1A
1R
1S
#330000
0V
0S
#335000
1V
1S
#340000
0V
0S
#345000
1V
1S
#350000
0V
0S
#355000
1V
1S
#360000
0V
0S
#365000
1V
1S
#370000
0V
0S
#375000
1V
1S
#380000
0V
0S
#385000
1V
1S
#390000
0V
0S
#395000
1V
1S
#400000
0V
0S
#405000
1V
1S
#410000
0V
0S
#415000
1U
1V
1S
#420000
0V
0S
#425000
0U
1V
05
1S
#430000
0V
0S
#435000
1V
1S
#440000
0V
0S
#445000
1V
1S
#450000
0V
0S
#455000
1V
1S
#460000
0V
0S
#465000
1V
1S
#470000
0V
0S
#475000
1V
1S
#480000
0V
0S
#485000
1V
1S
#490000
0V
0S
#495000
1V
1S
#500000
0V
0S
#505000
1V
1S
#510000
0V
0S
#515000
1V
1S
#520000
0V
0S
#525000
1V
1S
#530000
0V
0S
#535000
1V
1S
#540000
0V
0S
#545000
1V
1S
#550000
0V
0S
#555000
1V
1S
#560000
0V
0S
#565000
1V
1S
#570000
0V
0S
#575000
1U
1V
1S
#580000
0V
0S
#585000
0U
1V
1S
#590000
0V
0S
#595000
1V
1S
#600000
0V
0S
#605000
1V
1S
#610000
0V
0S
#615000
1V
1S
#620000
0V
0S
#625000
1V
1S
#630000
0V
0S
#635000
1V
1S
#640000
0V
0S
#645000
1V
1S
#650000
0V
0S
#655000
1V
1S
#660000
0V
0S
#665000
1V
1S
#670000
0V
0S
#675000
1V
1S
#680000
0V
0S
#685000
1V
1S
#690000
0V
0S
#695000
1V
1S
#700000
0V
0S
#705000
1V
1S
#710000
0V
0S
#715000
1V
1S
#720000
0V
0S
#725000
1V
1S
#730000
0V
0S
#735000
1U
1V
1S
#740000
0V
0S
#745000
0U
1V
15
1Q
1S
#750000
0V
0S
#755000
1V
1S
#760000
0V
0S
#765000
1V
1S
#770000
0V
0S
#775000
1V
1S
#780000
0V
0S
#785000
1V
1S
#790000
0V
0S
#795000
1V
1S
#800000
0V
0S
#805000
1V
1S
#810000
0V
0S
#815000
1V
1S
#820000
0V
0S
#825000
1V
14
1?
1=
07
1P
1N
0R
1S
#830000
0V
0S
#835000
1V
1S
#840000
0V
0S
#845000
1V
1S
#850000
0V
0S
#855000
1V
1S
#860000
0V
0S
#865000
1V
1S
#870000
0V
0S
#875000
1V
1S
#880000
0V
0S
#885000
1V
1S
#890000
0V
0S
#895000
1U
1V
1S
#900000
0V
0S
#905000
0U
1V
05
1S
#910000
0V
0S
#915000
1V
1S
#920000
0V
0S
#925000
1V
1S
#930000
0V
0S
#935000
1V
1S
#940000
0V
0S
#945000
1V
1S
#950000
0V
0S
#955000
1V
1S
#960000
0V
0S
#965000
1V
1S
#970000
0V
0S
#975000
1V
1S
#980000
0V
0S
#985000
1V
1S
#990000
0V
0S
#995000
1V
1S
#1000000
0V
0S
#1005000
1V
1S
#1010000
0V
0S
#1015000
1V
1S
#1020000
0V
0S
#1025000
1V
1S
#1030000
0V
0S
#1035000
1V
1S
#1040000
0V
0S
#1045000
1V
1S
#1050000
0V
0S
#1055000
1U
1V
1S
#1060000
0V
0S
#1065000
0U
1V
15
0Q
1S
#1070000
0V
0S
#1075000
1V
1S
#1080000
0V
0S
#1085000
1V
1S
#1090000
0V
0S
#1095000
1V
1S
#1100000
0V
0S
#1105000
1V
1S
#1110000
0V
0S
#1115000
1V
1S
#1120000
0V
0S
#1125000
1V
1S
#1130000
0V
0S
#1135000
1V
1S
#1140000
0V
0S
#1145000
1V
1S
#1150000
0V
0S
#1155000
1V
1S
#1160000
0V
0S
#1165000
1V
1S
#1170000
0V
0S
#1175000
1V
1S
#1180000
0V
0S
#1185000
1V
1S
#1190000
0V
0S
#1195000
1V
1S
#1200000
0V
0S
#1205000
1V
1S
#1210000
0V
0S
#1215000
1U
1V
1S
#1220000
0V
0S
#1225000
0U
1V
05
1S
#1230000
0V
0S
#1235000
1V
1S
#1240000
0V
0S
#1245000
1V
1S
#1250000
0V
0S
#1255000
1V
1S
#1260000
0V
0S
#1265000
1V
1S
#1270000
0V
0S
#1275000
1V
1S
#1280000
0V
0S
#1285000
1V
1S
#1290000
0V
0S
#1295000
1V
1S
#1300000
0V
0S
#1305000
1V
1S
#1310000
0V
0S
#1315000
1V
1S
#1320000
0V
0S
#1325000
1V
1S
#1330000
0V
0S
#1335000
1V
1S
#1340000
0V
0S
#1345000
1V
1S
#1350000
0V
0S
#1355000
1V
1S
#1360000
0V
0S
#1365000
1V
1S
#1370000
0V
0S
#1375000
1U
1V
1S
#1380000
0V
0S
#1385000
0U
1V
15
1Q
1S
#1390000
0V
0S
#1395000
1V
1S
#1400000
0V
0S
#1405000
1V
1S
#1410000
0V
0S
#1415000
1V
1S
#1420000
0V
0S
#1425000
1V
1S
#1430000
0V
0S
#1435000
1V
1S
#1440000
0V
0S
#1445000
1V
1S
#1450000
0V
0S
#1455000
1V
1S
#1460000
0V
0S
#1465000
1V
1S
#1470000
0V
0S
#1475000
1V
1S
#1480000
0V
0S
#1485000
1V
1S
#1490000
0V
0S
#1495000
1V
1S
#1500000
0V
0S
#1505000
1V
1S
#1510000
0V
0S
#1515000
1V
1S
#1520000
0V
0S
#1525000
1V
1S
#1530000
0V
0S
#1535000
1U
1V
1S
#1540000
0V
0S
#1545000
0U
1V
05
1S
#1550000
0V
0S
#1555000
1V
1S
#1560000
0V
0S
#1565000
1V
1S
#1570000
0V
0S
#1575000
1V
1S
#1580000
0V
0S
#1585000
1V
1S
#1590000
0V
0S
#1595000
1V
1S
#1600000
0V
0S
#1605000
1V
1S
#1610000
0V
0S
#1615000
1V
1S
#1620000
0V
0S
#1625000
1V
1S
#1630000
0V
0S
#1635000
1V
1S
#1640000
0V
0S
#1645000
1V
1S
#1650000
0V
0S
#1655000
1V
1S
#1660000
0V
0S
#1665000
1V
1S
#1670000
0V
0S
#1675000
1V
1S
#1680000
0V
0S
#1685000
1V
1S
#1690000
0V
0S
#1695000
1U
1V
1S
#1700000
0V
0S
#1705000
0U
1V
15
16
0Q
1S
#1710000
0V
0S
#1715000
1V
04
1S
#1720000
0V
0S
#1725000
1V
1S
#1730000
0V
0S
#1735000
1V
1S
#1740000
0V
0S
#1745000
1V
1S
#1750000
0V
0S
#1755000
1V
1S
#1760000
0V
0S
#1765000
1V
1S
#1770000
0V
0S
#1775000
1V
1S
#1780000
0V
0S
#1785000
1V
1S
#1790000
0V
0S
#1795000
1V
1S
#1800000
0V
0S
#1805000
1V
1S
#1810000
0V
0S
#1815000
1V
1S
#1820000
0V
0S
#1825000
1V
1S
#1830000
0V
0S
#1835000
1V
1S
#1840000
0V
0S
#1845000
1V
1S
#1850000
0V
0S
#1855000
1U
1V
1S
#1860000
0V
0S
#1865000
0U
1V
05
1S
#1870000
0V
0S
#1875000
1V
1S
#1880000
0V
0S
#1885000
1V
1S
#1890000
0V
0S
#1895000
1V
1S
#1900000
0V
0S
#1905000
1V
1S
#1910000
0V
0S
#1915000
1V
1S
#1920000
0V
0S
#1925000
1V
1S
#1930000
0V
0S
#1935000
1V
1S
#1940000
0V
0S
#1945000
1V
1S
#1950000
0V
0S
#1955000
1V
1S
#1960000
0V
0S
#1965000
1V
1S
#1970000
0V
0S
#1975000
1V
1S
#1980000
0V
0S
#1985000
1V
1S
#1990000
0V
0S
#1995000
1V
1S
#2000000
0V
0S
#2005000
1V
1S
#2010000
0V
0S
#2015000
1U
1V
1S
#2020000
0V
0S
#2025000
0U
1V
15
1S
#2030000
0V
0S
#2035000
1V
06
17
1H
1F
1R
1S
#2040000
0V
0S
#2045000
1V
1S
#2050000
0V
0S
#2055000
1V
1S
#2060000
0V
0S
#2065000
1V
1S
#2070000
0V
0S
#2075000
1V
1S
#2080000
0V
0S
#2085000
1V
1S
#2090000
0V
0S
#2095000
1V
1S
#2100000
0V
0S
#2105000
1V
1S
#2110000
0V
0S
#2115000
1V
1S
#2120000
0V
0S
#2125000
1V
1S
#2130000
0V
0S
#2135000
1V
1S
#2140000
0V
0S
#2145000
1V
1S
#2150000
0V
0S
#2155000
1V
1S
#2160000
0V
0S
#2165000
1V
1S
#2170000
0V
0S
#2175000
1U
1V
1S
#2180000
0V
0S
#2185000
0U
1V
05
1S
#2190000
0V
0S
#2195000
1V
1S
#2200000
0V
0S
#2205000
1V
1S
#2210000
0V
0S
#2215000
1V
1S
#2220000
0V
0S
#2225000
1V
1S
#2230000
0V
0S
#2235000
1V
1S
#2240000
0V
0S
#2245000
1V
1S
#2250000
0V
0S
#2255000
1V
1S
#2260000
0V
0S
#2265000
1V
1S
#2270000
0V
0S
#2275000
1V
1S
#2280000
0V
0S
#2285000
1V
1S
#2290000
0V
0S
#2295000
1V
1S
#2300000
0V
0S
#2305000
1V
1S
#2310000
0V
0S
#2315000
1V
1S
#2320000
0V
0S
#2325000
1V
1S
#2330000
0V
0S
#2335000
1U
1V
1S
#2340000
0V
0S
#2345000
0U
1V
15
1Q
1S
#2350000
0V
0S
#2355000
1V
1S
#2360000
0V
0S
#2365000
1V
1S
#2370000
0V
0S
#2375000
1V
1S
#2380000
0V
0S
#2385000
1V
1S
#2390000
0V
0S
#2395000
1V
1S
#2400000
0V
0S
#2405000
1V
1S
#2410000
0V
0S
#2415000
1V
1S
#2420000
0V
0S
#2425000
1V
1S
#2430000
0V
0S
#2435000
1V
1S
#2440000
0V
0S
#2445000
1V
1S
#2450000
0V
0S
#2455000
1V
1S
#2460000
0V
0S
#2465000
1V
1S
#2470000
0V
0S
#2475000
1V
1S
#2480000
0V
0S
#2485000
1V
1S
#2490000
0V
0S
#2495000
1U
1V
1S
#2500000
0V
0S
#2505000
0U
1V
0Q
1S
#2510000
0V
0S
#2515000
1V
1S
#2520000
0V
0S
#2525000
1V
1S
#2530000
0V
0S
#2535000
1V
1S
#2540000
0V
0S
#2545000
1V
1S
#2550000
0V
0S
#2555000
1V
1S
#2560000
0V
0S
#2565000
1V
1S
#2570000
0V
0S
#2575000
1V
1S
#2580000
0V
0S
#2585000
1V
1S
#2590000
0V
0S
#2595000
1V
1S
#2600000
0V
0S
#2605000
1V
1S
#2610000
0V
0S
#2615000
1V
1S
#2620000
0V
0S
#2625000
1V
1S
#2630000
0V
0S
#2635000
1V
1S
#2640000
0V
0S
#2645000
1V
1S
#2650000
0V
0S
#2655000
1U
1V
1S
#2660000
0V
0S
#2665000
0U
1V
1Q
1S
#2670000
0V
0S
#2675000
1V
1S
#2680000
0V
0S
#2685000
1V
1S
#2690000
0V
0S
#2695000
1V
1S
#2700000
0V
0S
#2705000
1V
1S
#2710000
0V
0S
#2715000
1V
1S
#2720000
0V
0S
#2725000
1V
1S
#2730000
0V
0S
#2735000
1V
1S
#2740000
0V
0S
#2745000
1V
1S
#2750000
0V
0S
#2755000
1V
1S
#2760000
0V
0S
#2765000
1V
1S
#2770000
0V
0S
#2775000
1V
1S
#2780000
0V
0S
#2785000
1V
1S
#2790000
0V
0S
#2795000
1V
1S
#2800000
0V
0S
#2805000
1V
1S
#2810000
0V
0S
#2815000
1U
1V
1S
#2820000
0V
0S
#2825000
0U
1V
0Q
1S
#2830000
0V
0S
#2835000
1V
1S
#2840000
0V
0S
#2845000
1V
1S
#2850000
0V
0S
#2855000
1V
1S
#2860000
0V
0S
#2865000
1V
1S
#2870000
0V
0S
#2875000
1V
1S
#2880000
0V
0S
#2885000
1V
1S
#2890000
0V
0S
#2895000
1V
1S
#2900000
0V
0S
#2905000
1V
1S
#2910000
0V
0S
#2915000
1V
1S
#2920000
0V
0S
#2925000
1V
1S
#2930000
0V
0S
#2935000
1V
1S
#2940000
0V
0S
#2945000
1V
1S
#2950000
0V
0S
#2955000
1V
1S
#2960000
0V
0S
#2965000
1V
1S
#2970000
0V
0S
#2975000
1U
1V
1S
#2980000
0V
0S
#2985000
0U
1V
05
1S
#2990000
0V
0S
#2995000
1V
1S
#3000000
0V
0S
#3005000
1V
1S
#3010000
0V
0S
#3015000
1V
1S
#3020000
0V
0S
#3025000
1V
1S
#3030000
0V
0S
#3035000
1V
1S
#3040000
0V
0S
#3045000
1V
1S
#3050000
0V
0S
#3055000
1V
1S
#3060000
0V
0S
#3065000
1V
1S
#3070000
0V
0S
#3075000
1V
1S
#3080000
0V
0S
#3085000
1V
1S
#3090000
0V
0S
#3095000
1V
1S
#3100000
0V
0S
#3105000
1V
1S
#3110000
0V
0S
#3115000
1V
1S
#3120000
0V
0S
#3125000
1V
1S
#3130000
0V
0S
#3135000
1U
1V
1S
#3140000
0V
0S
#3145000
0U
1V
15
1Q
1S
#3150000
0V
0S
#3155000
1V
1S
#3160000
0V
0S
#3165000
1V
1S
#3170000
0V
0S
#3175000
1V
1S
#3180000
0V
0S
#3185000
1V
1S
#3190000
0V
0S
#3195000
1V
1S
#3200000
0V
0S
#3205000
1V
1S
#3210000
0V
0S
#3215000
1V
1S
#3220000
0V
0S
#3225000
1V
1S
#3230000
0V
0S
#3235000
1V
1S
#3240000
0V
0S
#3245000
1V
1S
#3250000
0V
0S
#3255000
1V
1S
#3260000
0V
0S
#3265000
1V
1S
#3270000
0V
0S
#3275000
1V
1S
#3280000
0V
0S
#3285000
1V
1S
#3290000
0V
0S
#3295000
1U
1V
1S
#3300000
0V
0S
#3305000
0U
1V
05
1S
#3310000
0V
0S
#3315000
1V
1S
#3320000
0V
0S
#3325000
1V
1S
#3330000
0V
0S
#3335000
1V
1S
#3340000
0V
0S
#3345000
1V
1S
#3350000
0V
0S
#3355000
1V
1S
#3360000
0V
0S
#3365000
1V
1S
#3370000
0V
0S
#3375000
1V
1S
#3380000
0V
0S
#3385000
1V
1S
#3390000
0V
0S
#3395000
1V
1S
#3400000
0V
0S
#3405000
1V
1S
#3410000
0V
0S
#3415000
1V
1S
#3420000
0V
0S
#3425000
1V
1S
#3430000
0V
0S
#3435000
1V
1S
#3440000
0V
0S
#3445000
1V
1S
#3450000
0V
0S
#3455000
1U
1V
1S
#3460000
0V
0S
#3465000
0U
1V
15
16
0Q
1S
#3470000
0V
0S
#3475000
1V
1S
#3480000
0V
0S
#3485000
1V
1S
#3490000
0V
0S
#3495000
1V
1S
#3500000
0V
0S
#3505000
1V
1S
#3510000
0V
0S
#3515000
1V
1S
#3520000
0V
0S
#3525000
1V
1S
#3530000
0V
0S
#3535000
1V
1S
#3540000
0V
0S
#3545000
1V
1S
#3550000
0V
0S
#3555000
1V
1S
#3560000
0V
0S
#3565000
1V
1S
#3570000
0V
0S
#3575000
1V
1S
#3580000
0V
0S
#3585000
1V
1S
#3590000
0V
0S
#3595000
1V
1S
#3600000
0V
0S
#3605000
1V
1S
#3610000
0V
0S
#3615000
1U
1V
1S
#3620000
0V
0S
#3625000
0U
1V
05
1S
#3630000
0V
0S
#3635000
1V
1S
#3640000
0V
0S
#3645000
1V
1S
#3650000
0V
0S
#3655000
1V
1S
#3660000
0V
0S
#3665000
1V
1S
#3670000
0V
0S
#3675000
1V
1S
#3680000
0V
0S
#3685000
1V
1S
#3690000
0V
0S
#3695000
1V
1S
#3700000
0V
0S
#3705000
1V
1S
#3710000
0V
0S
#3715000
1V
14
0?
0=
0:
07
0P
0N
0K
0R
1S
#3720000
0V
0S
#3725000
1V
04
1S
#3730000
0V
0S
#3735000
1V
1S
#3740000
0V
0S
#3745000
1V
1S
#3750000
0V
0S
#3755000
1V
1S
#3760000
0V
0S
#3765000
1V
1S
#3770000
0V
0S
#3775000
1U
1V
1S
#3780000
0V
0S
#3785000
0U
1V
15
1S
#3790000
0V
0S
#3795000
1V
06
17
0H
0F
0C
1R
1S
#3800000
0V
0S
#3805000
1V
1S
#3810000
0V
0S
#3815000
1V
1S
#3820000
0V
0S
#3825000
1V
1S
#3830000
0V
0S
#3835000
1V
1S
#3840000
0V
0S
#3845000
1V
1S
#3850000
0V
0S
#3855000
1V
1S
#3860000
0V
0S
#3865000
1V
1S
#3870000
0V
0S
#3875000
1V
1S
#3880000
0V
0S
#3885000
1V
1S
#3890000
0V
0S
#3895000
1V
1S
#3900000
0V
0S
#3905000
1V
1S
#3910000
0V
0S
#3915000
1V
1S
#3920000
0V
0S
#3925000
1V
1S
#3930000
0V
0S
#3935000
1U
1V
1S
#3940000
0V
0S
#3945000
0U
1V
05
1S
#3950000
0V
0S
#3955000
1V
1S
#3960000
0V
0S
#3965000
1V
1S
#3970000
0V
0S
#3975000
1V
1S
#3980000
0V
0S
#3985000
1V
1S
#3990000
0V
0S
#3995000
1V
1S
#4000000
0V
0S
#4005000
1V
1S
#4010000
0V
0S
#4015000
1V
1S
#4020000
0V
0S
#4025000
1V
1S
#4030000
0V
0S
#4035000
1V
1S
#4040000
0V
0S
#4045000
1V
1S
#4050000
0V
0S
#4055000
1V
1S
#4060000
0V
0S
#4065000
1V
1S
#4070000
0V
0S
#4075000
1V
1S
#4080000
0V
0S
#4085000
1V
1S
#4090000
0V
0S
#4095000
1U
1V
1S
#4100000
0V
0S
#4105000
0U
1V
1S
#4110000
0V
0S
#4115000
1V
1S
#4120000
0V
0S
#4125000
1V
1S
#4130000
0V
0S
#4135000
1V
1S
#4140000
0V
0S
#4145000
1V
1S
#4150000
0V
0S
#4155000
1V
1S
#4160000
0V
0S
#4165000
1V
1S
#4170000
0V
0S
#4175000
1V
1S
#4180000
0V
0S
#4185000
1V
1S
#4190000
0V
0S
#4195000
1V
1S
#4200000
0V
0S
#4205000
1V
1S
#4210000
0V
0S
#4215000
1V
1S
#4220000
0V
0S
#4225000
1V
1S
#4230000
0V
0S
#4235000
1V
1S
#4240000
0V
0S
#4245000
1V
1S
#4250000
0V
0S
#4255000
1U
1V
1S
#4260000
0V
0S
#4265000
0U
1V
15
1Q
1S
#4270000
0V
0S
#4275000
1V
1S
#4280000
0V
0S
#4285000
1V
1S
#4290000
0V
0S
#4295000
1V
1S
#4300000
0V
0S
#4305000
1V
1S
#4310000
0V
0S
#4315000
1V
1S
#4320000
0V
0S
#4325000
1V
1S
#4330000
0V
0S
#4335000
1V
1S
#4340000
0V
0S
#4345000
1V
1S
#4350000
0V
0S
#4355000
1V
1S
#4360000
0V
0S
#4365000
1V
1S
#4370000
0V
0S
#4375000
1V
1S
#4380000
0V
0S
#4385000
1V
1S
#4390000
0V
0S
#4395000
1V
1S
#4400000
0V
0S
#4405000
1V
1S
#4410000
0V
0S
#4415000
1U
1V
1S
#4420000
0V
0S
#4425000
0U
1V
05
1S
#4430000
0V
0S
#4435000
1V
1S
#4440000
0V
0S
#4445000
1V
1S
#4450000
0V
0S
#4455000
1V
1S
#4460000
0V
0S
#4465000
1V
1S
#4470000
0V
0S
#4475000
1V
1S
#4480000
0V
0S
#4485000
1V
1S
#4490000
0V
0S
#4495000
1V
1S
#4500000
0V
0S
#4505000
1V
1S
#4510000
0V
0S
#4515000
1V
1S
#4520000
0V
0S
#4525000
1V
1S
#4530000
0V
0S
#4535000
1V
1S
#4540000
0V
0S
#4545000
1V
1S
#4550000
0V
0S
#4555000
1V
1S
#4560000
0V
0S
#4565000
1V
1S
#4570000
0V
0S
#4575000
1U
1V
1S
#4580000
0V
0S
